tangosuper
